mongoserializer/fields.py
mongoserializer/methods.py
mongoserializer/serializer.py
mongoserializer-1.0.1.dist-info/LICENSE
mongoserializer-1.0.1.dist-info/METADATA
mongoserializer-1.0.1.dist-info/WHEEL
mongoserializer-1.0.1.dist-info/top_level.txt
mongoserializer-1.0.1.dist-info/RECORD
