Metadata-Version: 2.1
Name: mongoserializer
Version: 1.0.1
Summary: One of the best practices for interacting with MongoDB in a Django REST environment
Home-page: https://github.com/ahmadekhalili/onetomultipleimage
Author: Ahmad Khalili
Author-email: ahmadkhalili2020@gmail.com
License: MIT
Classifier: Framework :: Django
Classifier: Framework :: Django :: 3
Classifier: Framework :: Django :: 4
Classifier: Programming Language :: Python :: 3
Classifier: Programming Language :: Python :: 3.7
Classifier: Programming Language :: Python :: 3.8
Classifier: Programming Language :: Python :: 3.9
Classifier: Programming Language :: Python :: 3.10
Classifier: License :: OSI Approved :: MIT License
License-File: LICENSE
Requires-Dist: django
Requires-Dist: djangorestframework
Requires-Dist: pymongo
Provides-Extra: jalali
Requires-Dist: jdatetime; extra == "jalali"
